kcl_lib-0.12.3.dist-info/METADATA
kcl_lib-0.12.3.dist-info/WHEEL
kcl_lib/__init__.py
kcl_lib/_kcl_lib.cpython-37m-aarch64-linux-gnu.so
kcl_lib/api/__init__.py
kcl_lib/api/service.py
kcl_lib/api/spec_pb2.py
kcl_lib/api/spec_pb2.pyi
kcl_lib/plugin/__init__.py
kcl_lib/plugin/plugin.py
kcl_lib-0.12.3.dist-info/RECORD
