Metadata-Version: 2.4
Name: kcl_lib
Version: 0.12.3
Classifier: Programming Language :: Rust
Classifier: Programming Language :: Python :: Implementation :: CPython
Classifier: Programming Language :: Python :: Implementation :: PyPy
Requires-Dist: protobuf>=6.33.1
Requires-Dist: pdoc ; extra == 'docs'
Requires-Dist: ruff ; extra == 'lint'
Requires-Dist: pytest ; extra == 'test'
Provides-Extra: docs
Provides-Extra: lint
Provides-Extra: test
Summary: KCL Programming Language Python Lib
License: Apache-2.0
Requires-Python: >=3.7
Project-URL: Documentation, https://kcl-lang.io
Project-URL: Homepage, https://kcl-lang.io
Project-URL: Repository, https://github.com/kcl-lang/kcl
